myzero/__init__.py
myzero/app.py
myzero/middleware.py
myzero/request.py
myzero/response.py
myzero/routing.py
myzero/server.py
myzero/setup.py
myzero/static.py
zerofl-0.1.11.dist-info/LICENSE
zerofl-0.1.11.dist-info/METADATA
zerofl-0.1.11.dist-info/WHEEL
zerofl-0.1.11.dist-info/top_level.txt
zerofl-0.1.11.dist-info/RECORD
