Metadata-Version: 2.1
Name: zerofl
Version: 0.1.11
Summary: A lightweight, production-ready micro web framework in Python.
Author: MD Imran
License: MIT
Classifier: Programming Language :: Python :: 3
Classifier: License :: OSI Approved :: MIT License
Classifier: Operating System :: OS Independent
Requires-Python: >=3.7
License-File: LICENSE
